<?xml version="1.0" encoding="UTF-8"?>
<log date="2015-08-29T19:05:30.175+01:00">
 <info method="org.xmlcml.ami2.plugins.phylotree.PhyloTreeArgProcessor.ensureOutputDirectory" message="PhyloTree output to: target/junk/1440871530175; suggest you setOutputDir()" millis="0"/>
 <error method="org.xmlcml.ami2.plugins.phylotree.nexml.NexmlFactory.checkEdges" message="duplicate edge: NT1.50=&gt;NT1.48" millis="8022"/>
 <error method="org.xmlcml.ami2.plugins.phylotree.nexml.NexmlFactory.checkEdges" message="edge target NT1.48 == source NT1.48" millis="8022"/>
 <error method="org.xmlcml.ami2.plugins.phylotree.PhyloTreeArgProcessor.processOtu" message="ERR_BAD_SYNTAX [PpDB(Y10095)]" millis="8836"/>
 <error method="org.xmlcml.ami2.plugins.phylotree.PhyloTreeArgProcessor.processOtu" message="ERR_BAD_SYNTAX [AAY(X68373)]" millis="8837"/>
 <error method="org.xmlcml.ami2.plugins.phylotree.PhyloTreeArgProcessor.processOtu" message="ERR_BAD_SYNTAX [AusGY (X95706)]" millis="8837"/>
 <error method="org.xmlcml.ami2.plugins.phylotree.PhyloTreeArgProcessor.processOtu" message="ERR_BAD_SYNTAX [STOL (X76427)]" millis="8837"/>
 <error method="org.xmlcml.ami2.plugins.phylotree.PhyloTreeArgProcessor.processOtu" message="ERR_BAD_SYNTAX [BB (L33760)]" millis="8837"/>
 <error method="org.xmlcml.ami2.plugins.phylotree.PhyloTreeArgProcessor.processOtu" message="ERR_BAD_SYNTAX [A. Iaidlawii JA1 (M23932)]" millis="8837"/>
 <error method="org.xmlcml.ami2.plugins.phylotree.PhyloTreeArgProcessor.processOtu" message="ERR_BAD_SYNTAX [awe (X76431)]" millis="8837"/>
 <error method="org.xmlcml.ami2.plugins.phylotree.PhyloTreeArgProcessor.processOtu" message="ERR_BAD_SYNTAX [IBS(Y16391)]" millis="8838"/>
 <error method="org.xmlcml.ami2.plugins.phylotree.PhyloTreeArgProcessor.processOtu" message="ERR_BAD_SYNTAX []" millis="8838"/>
 <error method="org.xmlcml.ami2.plugins.phylotree.PhyloTreeArgProcessor.processOtu" message="ERR_BAD_SYNTAX [ESFYC -AYO29540)]" millis="8838"/>
 <error method="org.xmlcml.ami2.plugins.phylotree.PhyloTreeArgProcessor.processOtu" message="ERR_BAD_SYNTAX [AT (X68375)]" millis="8838"/>
 <error method="org.xmlcml.ami2.plugins.phylotree.PhyloTreeArgProcessor.processOtu" message="ERR_BAD_SYNTAX [wx (L04682)]" millis="8838"/>
 <error method="org.xmlcml.ami2.plugins.phylotree.PhyloTreeArgProcessor.processOtu" message="ERR_BAD_SYNTAX [CYE (AF175304)]" millis="8838"/>
 <error method="org.xmlcml.ami2.plugins.phylotree.PhyloTreeArgProcessor.processOtu" message="ERR_BAD_SYNTAX [PPWB (AF248957)]" millis="8838"/>
 <error method="org.xmlcml.ami2.plugins.phylotree.PhyloTreeArgProcessor.processOtu" message="ERR_BAD_SYNTAX [HibWB26 (AF147708)]" millis="8839"/>
 <error method="org.xmlcml.ami2.plugins.phylotree.PhyloTreeArgProcessor.processOtu" message="ERR_BAD_SYNTAX [PpYC (Y10097)]" millis="8839"/>
 <error method="org.xmlcml.ami2.plugins.phylotree.PhyloTreeArgProcessor.processOtu" message="ERR_BAD_SYNTAX [PnWB (L33765)]" millis="8839"/>
 <error method="org.xmlcml.ami2.plugins.phylotree.PhyloTreeArgProcessor.processOtu" message="ERR_BAD_SYNTAX [PEP (Y16393)]" millis="8839"/>
 <error method="org.xmlcml.ami2.plugins.phylotree.PhyloTreeArgProcessor.processOtu" message="ERR_BAD_SYNTAX [wan). (U15442)]" millis="8839"/>
 <error method="org.xmlcml.ami2.plugins.phylotree.PhyloTreeArgProcessor.processOtu" message="ERR_BAD_SYNTAX [FBP (X83432)]" millis="8839"/>
 <error method="org.xmlcml.ami2.plugins.phylotree.PhyloTreeArgProcessor.processOtu" message="ERR_BAD_SYNTAX [SCWL (X76432)]" millis="8839"/>
 <error method="org.xmlcml.ami2.plugins.phylotree.PhyloTreeArgProcessor.processOtu" message="ERR_BAD_SYNTAX [CIRP (X83438)]" millis="8840"/>
 <error method="org.xmlcml.ami2.plugins.phylotree.PhyloTreeArgProcessor.processOtu" message="ERR_BAD_SYNTAX [LY (AF498309)]" millis="8840"/>
 <error method="org.xmlcml.ami2.plugins.phylotree.PhyloTreeArgProcessor.processOtu" message="ERR_BAD_SYNTAX []" millis="8840"/>
 <error method="org.xmlcml.ami2.plugins.phylotree.PhyloTreeArgProcessor.processOtu" message="ERR_BAD_SYNTAX [TLD (X801 17)]" millis="8840"/>
 <error method="org.xmlcml.ami2.plugins.phylotree.PhyloTreeArgProcessor.processOtu" message="ERR_BAD_SYNTAX [BGWL (Y16388)]" millis="8840"/>
 <error method="org.xmlcml.ami2.plugins.phylotree.PhyloTreeArgProcessor.processOtu" message="ERR_BAD_SYNTAX [LfWB (AF248956)]" millis="8840"/>
 <error method="org.xmlcml.ami2.plugins.phylotree.PhyloTreeArgProcessor.processOtu" message="ERR_BAD_SYNTAX [BLL(AF228052)]" millis="8840"/>
 <error method="org.xmlcml.ami2.plugins.phylotree.PhyloTreeArgProcessor.processOtu" message="ERR_BAD_SYNTAX [CLY5 (AY197659)]" millis="8841"/>
 <error method="org.xmlcml.ami2.plugins.phylotree.PhyloTreeArgProcessor.processOtu" message="ERR_BAD_SYNTAX [PY-In (AY197660)]" millis="8841"/>
 <error method="org.xmlcml.ami2.plugins.phylotree.PhyloTreeArgProcessor.processOtu" message="ERR_BAD_SYNTAX [CP (L33761)]" millis="8841"/>
 <error method="org.xmlcml.ami2.plugins.phylotree.PhyloTreeArgProcessor.processOtu" message="ERR_BAD_SYNTAX [EY626 (AY197657)]" millis="8841"/>
 <error method="org.xmlcml.ami2.plugins.phylotree.PhyloTreeArgProcessor.processOtu" message="ERR_BAD_SYNTAX [EY1T (AY197655)]" millis="8841"/>
 <error method="org.xmlcml.ami2.plugins.phylotree.PhyloTreeArgProcessor.processOtu" message="ERR_BAD_SYNTAX [SpaWB251 (AY197653)]" millis="8841"/>
 <error method="org.xmlcml.ami2.plugins.phylotree.PhyloTreeArgProcessor.processOtu" message="ERR_BAD_SYNTAX [SpaWB229 (AY197652)]" millis="8841"/>
 <error method="org.xmlcml.ami2.plugins.phylotree.PhyloTreeArgProcessor.processOtu" message="ERR_BAD_SYNTAX [HD1 (AY197654)]" millis="8842"/>
 <error method="org.xmlcml.ami2.plugins.phylotree.PhyloTreeArgProcessor.processOtu" message="ERR_BAD_SYNTAX [ALY1068 (AY197647)]" millis="8842"/>
 <error method="org.xmlcml.ami2.plugins.phylotree.PhyloTreeArgProcessor.processOtu" message="ERR_BAD_SYNTAX [ALY882 (AY197642)]" millis="8842"/>
 <error method="org.xmlcml.ami2.plugins.phylotree.PhyloTreeArgProcessor.processOtu" message="ERR_BAD_SYNTAX [FD7O (AY197643)]" millis="8842"/>
 <error method="org.xmlcml.ami2.plugins.phylotree.PhyloTreeArgProcessor.processOtu" message="ERR_BAD_SYNTAX [FD-D (AY197644)]" millis="8842"/>
 <error method="org.xmlcml.ami2.plugins.phylotree.PhyloTreeArgProcessor.processOtu" message="ERR_BAD_SYNTAX [AshY (AF189215)]" millis="8842"/>
 <error method="org.xmlcml.ami2.plugins.phylotree.PhyloTreeArgProcessor.processOtu" message="ERR_BAD_SYNTAX [RuS400 (AY197649)]" millis="8843"/>
 <error method="org.xmlcml.ami2.plugins.phylotree.PhyloTreeArgProcessor.processOtu" message="ERR_BAD_SYNTAX [RuSR19 (AY197651)]" millis="8843"/>
 <error method="org.xmlcml.ami2.plugins.phylotree.PhyloTreeArgProcessor.processOtu" message="ERR_BAD_SYNTAX [RUS (AY197648)]" millis="8843"/>
 <error method="org.xmlcml.ami2.plugins.phylotree.PhyloTreeArgProcessor.pruneBadTips" message="cannot delete tip java.lang.RuntimeException: NULL parent node for: otu1; not deleted" millis="8843"/>
 <error method="org.xmlcml.ami2.plugins.phylotree.PhyloTreeArgProcessor.pruneBadTips" message="cannot delete tip java.lang.RuntimeException: NULL parent node for: otu2; not deleted" millis="8843"/>
 <error method="org.xmlcml.ami2.plugins.phylotree.PhyloTreeArgProcessor.pruneBadTips" message="cannot delete tip java.lang.RuntimeException: NULL parent node for: otu3; not deleted" millis="8843"/>
 <error method="org.xmlcml.ami2.plugins.phylotree.PhyloTreeArgProcessor.pruneBadTips" message="cannot delete tip java.lang.RuntimeException: NULL parent node for: otu4; not deleted" millis="8843"/>
 <error method="org.xmlcml.ami2.plugins.phylotree.PhyloTreeArgProcessor.pruneBadTips" message="cannot delete tip java.lang.RuntimeException: NULL parent node for: otu5; not deleted" millis="8843"/>
 <error method="org.xmlcml.ami2.plugins.phylotree.PhyloTreeArgProcessor.pruneBadTips" message="cannot delete tip java.lang.RuntimeException: NULL parent node for: otu6; not deleted" millis="8844"/>
 <error method="org.xmlcml.ami2.plugins.phylotree.PhyloTreeArgProcessor.pruneBadTips" message="cannot delete tip java.lang.RuntimeException: NULL parent node for: otu7; not deleted" millis="8844"/>
 <error method="org.xmlcml.ami2.plugins.phylotree.PhyloTreeArgProcessor.pruneBadTips" message="cannot delete tip java.lang.RuntimeException: NULL parent node for: otu8; not deleted" millis="8844"/>
 <error method="org.xmlcml.ami2.plugins.phylotree.PhyloTreeArgProcessor.pruneBadTips" message="cannot delete tip java.lang.RuntimeException: NULL parent node for: otu9; not deleted" millis="8844"/>
 <error method="org.xmlcml.ami2.plugins.phylotree.PhyloTreeArgProcessor.pruneBadTips" message="cannot delete tip java.lang.RuntimeException: NULL parent node for: otu10; not deleted" millis="8844"/>
 <error method="org.xmlcml.ami2.plugins.phylotree.PhyloTreeArgProcessor.pruneBadTips" message="cannot delete tip java.lang.RuntimeException: NULL parent node for: otu11; not deleted" millis="8844"/>
 <error method="org.xmlcml.ami2.plugins.phylotree.PhyloTreeArgProcessor.pruneBadTips" message="cannot delete tip java.lang.RuntimeException: NULL parent node for: otu12; not deleted" millis="8844"/>
 <error method="org.xmlcml.ami2.plugins.phylotree.PhyloTreeArgProcessor.pruneBadTips" message="cannot delete tip java.lang.RuntimeException: NULL parent node for: otu13; not deleted" millis="8844"/>
 <error method="org.xmlcml.ami2.plugins.phylotree.PhyloTreeArgProcessor.pruneBadTips" message="cannot delete tip java.lang.RuntimeException: NULL parent node for: otu14; not deleted" millis="8844"/>
 <error method="org.xmlcml.ami2.plugins.phylotree.PhyloTreeArgProcessor.pruneBadTips" message="cannot delete tip java.lang.RuntimeException: NULL parent node for: otu15; not deleted" millis="8844"/>
 <error method="org.xmlcml.ami2.plugins.phylotree.PhyloTreeArgProcessor.pruneBadTips" message="cannot delete tip java.lang.RuntimeException: NULL parent node for: otu16; not deleted" millis="8844"/>
 <error method="org.xmlcml.ami2.plugins.phylotree.PhyloTreeArgProcessor.pruneBadTips" message="cannot delete tip java.lang.RuntimeException: NULL parent node for: otu17; not deleted" millis="8845"/>
 <error method="org.xmlcml.ami2.plugins.phylotree.PhyloTreeArgProcessor.pruneBadTips" message="cannot delete tip java.lang.RuntimeException: NULL parent node for: otu18; not deleted" millis="8845"/>
 <error method="org.xmlcml.ami2.plugins.phylotree.PhyloTreeArgProcessor.pruneBadTips" message="cannot delete tip java.lang.RuntimeException: NULL parent node for: otu19; not deleted" millis="8845"/>
 <error method="org.xmlcml.ami2.plugins.phylotree.PhyloTreeArgProcessor.pruneBadTips" message="cannot delete tip java.lang.RuntimeException: NULL parent node for: otu20; not deleted" millis="8845"/>
 <error method="org.xmlcml.ami2.plugins.phylotree.PhyloTreeArgProcessor.pruneBadTips" message="cannot delete tip java.lang.RuntimeException: NULL parent node for: otu21; not deleted" millis="8845"/>
 <error method="org.xmlcml.ami2.plugins.phylotree.PhyloTreeArgProcessor.pruneBadTips" message="cannot delete tip java.lang.RuntimeException: NULL parent node for: otu22; not deleted" millis="8845"/>
 <error method="org.xmlcml.ami2.plugins.phylotree.PhyloTreeArgProcessor.pruneBadTips" message="cannot delete tip java.lang.RuntimeException: NULL parent node for: otu23; not deleted" millis="8845"/>
 <error method="org.xmlcml.ami2.plugins.phylotree.PhyloTreeArgProcessor.pruneBadTips" message="cannot delete tip java.lang.RuntimeException: NULL parent node for: otu24; not deleted" millis="8845"/>
 <error method="org.xmlcml.ami2.plugins.phylotree.PhyloTreeArgProcessor.pruneBadTips" message="cannot delete tip java.lang.RuntimeException: NULL parent node for: otu25; not deleted" millis="8845"/>
 <error method="org.xmlcml.ami2.plugins.phylotree.PhyloTreeArgProcessor.pruneBadTips" message="cannot delete tip java.lang.RuntimeException: NULL parent node for: otu26; not deleted" millis="8845"/>
 <error method="org.xmlcml.ami2.plugins.phylotree.PhyloTreeArgProcessor.pruneBadTips" message="cannot delete tip java.lang.RuntimeException: NULL parent node for: otu27; not deleted" millis="8845"/>
 <error method="org.xmlcml.ami2.plugins.phylotree.PhyloTreeArgProcessor.pruneBadTips" message="cannot delete tip java.lang.RuntimeException: NULL parent node for: otu28; not deleted" millis="8846"/>
 <error method="org.xmlcml.ami2.plugins.phylotree.PhyloTreeArgProcessor.pruneBadTips" message="cannot delete tip java.lang.RuntimeException: NULL parent node for: otu29; not deleted" millis="8846"/>
 <error method="org.xmlcml.ami2.plugins.phylotree.PhyloTreeArgProcessor.pruneBadTips" message="cannot delete tip java.lang.RuntimeException: NULL parent node for: otu30; not deleted" millis="8846"/>
 <error method="org.xmlcml.ami2.plugins.phylotree.PhyloTreeArgProcessor.pruneBadTips" message="cannot delete tip java.lang.RuntimeException: NULL parent node for: otu31; not deleted" millis="8846"/>
 <error method="org.xmlcml.ami2.plugins.phylotree.PhyloTreeArgProcessor.pruneBadTips" message="cannot delete tip java.lang.RuntimeException: NULL parent node for: otu32; not deleted" millis="8846"/>
 <error method="org.xmlcml.ami2.plugins.phylotree.PhyloTreeArgProcessor.pruneBadTips" message="cannot delete tip java.lang.RuntimeException: NULL parent node for: otu33; not deleted" millis="8846"/>
 <error method="org.xmlcml.ami2.plugins.phylotree.PhyloTreeArgProcessor.pruneBadTips" message="cannot delete tip java.lang.RuntimeException: NULL parent node for: otu34; not deleted" millis="8846"/>
 <error method="org.xmlcml.ami2.plugins.phylotree.PhyloTreeArgProcessor.pruneBadTips" message="cannot delete tip java.lang.RuntimeException: NULL parent node for: otu35; not deleted" millis="8846"/>
 <error method="org.xmlcml.ami2.plugins.phylotree.PhyloTreeArgProcessor.pruneBadTips" message="cannot delete tip java.lang.RuntimeException: NULL parent node for: otu36; not deleted" millis="8846"/>
 <error method="org.xmlcml.ami2.plugins.phylotree.PhyloTreeArgProcessor.pruneBadTips" message="cannot delete tip java.lang.RuntimeException: NULL parent node for: otu37; not deleted" millis="8846"/>
 <error method="org.xmlcml.ami2.plugins.phylotree.PhyloTreeArgProcessor.pruneBadTips" message="cannot delete tip java.lang.RuntimeException: NULL parent node for: otu38; not deleted" millis="8846"/>
 <error method="org.xmlcml.ami2.plugins.phylotree.PhyloTreeArgProcessor.pruneBadTips" message="cannot delete tip java.lang.RuntimeException: NULL parent node for: otu39; not deleted" millis="8847"/>
 <error method="org.xmlcml.ami2.plugins.phylotree.PhyloTreeArgProcessor.pruneBadTips" message="cannot delete tip java.lang.RuntimeException: NULL parent node for: otu40; not deleted" millis="8847"/>
 <error method="org.xmlcml.ami2.plugins.phylotree.PhyloTreeArgProcessor.pruneBadTips" message="cannot delete tip java.lang.RuntimeException: NULL parent node for: otu41; not deleted" millis="8847"/>
 <error method="org.xmlcml.ami2.plugins.phylotree.PhyloTreeArgProcessor.pruneBadTips" message="cannot delete tip java.lang.RuntimeException: NULL parent node for: otu42; not deleted" millis="8847"/>
 <error method="org.xmlcml.ami2.plugins.phylotree.PhyloTreeArgProcessor.pruneBadTips" message="cannot delete tip java.lang.RuntimeException: NULL parent node for: otu43; not deleted" millis="8847"/>
 <error method="org.xmlcml.ami2.plugins.phylotree.PhyloTreeArgProcessor.pruneBadTips" message="cannot delete tip java.lang.RuntimeException: NULL parent node for: otu44; not deleted" millis="8847"/>
 <info method="org.xmlcml.ami2.plugins.phylotree.PhyloTreeArgProcessor.createTree" message="Analyzed pixels for tree successfully" millis="8850"/>
 <info method="org.xmlcml.ami2.plugins.phylotree.PhyloTreeArgProcessor.outputNexml" message="wrote NEXML: ../ijsem/500E/ijs.0.02697-0-004.pbm/results/phylotree/001.nexml.xml" millis="8852"/>
 <info method="org.xmlcml.ami2.plugins.phylotree.PhyloTreeArgProcessor.outputNewick" message="wrote Newick: ../ijsem/500E/ijs.0.02697-0-004.pbm/results/phylotree/001.nwk" millis="8853"/>
 <info method="org.xmlcml.ami2.plugins.phylotree.PhyloTreeArgProcessor.outputHocrSvg" message="wrote HOCSVG: ../ijsem/500E/ijs.0.02697-0-004.pbm/results/phylotree/001.hocr.svg" millis="8859"/>
 <info method="org.xmlcml.ami2.plugins.phylotree.PhyloTreeArgProcessor.outputSvg" message="wrote HOCSVG: ../ijsem/500E/ijs.0.02697-0-004.pbm/results/phylotree/001.svg" millis="8871"/>
</log>
