<?xml version="1.0" encoding="UTF-8"?>
<log date="2015-08-29T14:07:12.919+01:00">
 <info method="org.xmlcml.ami2.plugins.phylotree.PhyloTreeArgProcessor.ensureOutputDirectory" message="PhyloTree output to: target/junk/1440853632919; suggest you setOutputDir()" millis="0"/>
 <error method="org.xmlcml.ami2.plugins.phylotree.PhyloTreeArgProcessor.processOtu" message="ERR_BAD_SYNTAX [E. solitarius LMG 128907 (AJ843467)]" millis="11605"/>
 <error method="org.xmlcml.ami2.plugins.phylotree.PhyloTreeArgProcessor.processOtu" message="ERR_BAD_SYNTAX []" millis="11606"/>
 <error method="org.xmlcml.ami2.plugins.phylotree.PhyloTreeArgProcessor.processOtu" message="ERR_BAD_SYNTAX [g.rn.rn.rn.rn.rn.rn]" millis="11606"/>
 <error method="org.xmlcml.ami2.plugins.phylotree.PhyloTreeArgProcessor.processOtu" message="ERR_BAD_SYNTAX []" millis="11606"/>
 <error method="org.xmlcml.ami2.plugins.phylotree.PhyloTreeArgProcessor.processOtu" message="ERR_BAD_SYNTAX []" millis="11606"/>
 <error method="org.xmlcml.ami2.plugins.phylotree.PhyloTreeArgProcessor.processOtu" message="ERR_BAD_SYNTAX []" millis="11606"/>
 <error method="org.xmlcml.ami2.plugins.phylotree.PhyloTreeArgProcessor.processOtu" message="ERR_BAD_SYNTAX [rn.rn.rn.rnO.rn.rn.rn]" millis="11606"/>
 <error method="org.xmlcml.ami2.plugins.phylotree.PhyloTreeArgProcessor.processOtu" message="ERR_BAD_SYNTAX [E. saccharolyticus LMG 114277 (AJ843376)]" millis="11606"/>
 <error method="org.xmlcml.ami2.plugins.phylotree.PhyloTreeArgProcessor.processOtu" message="ERR_BAD_SYNTAX [E. sulfureus LMG 130847 (AJ843427)]" millis="11606"/>
 <error method="org.xmlcml.ami2.plugins.phylotree.PhyloTreeArgProcessor.processOtu" message="ERR_BAD_SYNTAX [E. dispar LMG 135217 (AJ843382)]" millis="11606"/>
 <error method="org.xmlcml.ami2.plugins.phylotree.PhyloTreeArgProcessor.processOtu" message="ERR_BAD_SYNTAX [E. mundtii LMG 107487 (AJ843374)]" millis="11606"/>
 <error method="org.xmlcml.ami2.plugins.phylotree.PhyloTreeArgProcessor.processOtu" message="ERR_BAD_SYNTAX [E. villorum LMG 122877 (AJ843378)]" millis="11607"/>
 <error method="org.xmlcml.ami2.plugins.phylotree.PhyloTreeArgProcessor.processOtu" message="ERR_BAD_SYNTAX [E. durans LMG 107467 (AJ843373)]" millis="11607"/>
 <error method="org.xmlcml.ami2.plugins.phylotree.PhyloTreeArgProcessor.processOtu" message="ERR_BAD_SYNTAX [E. hirae LMG 63997 (AJ843420)]" millis="11607"/>
 <error method="org.xmlcml.ami2.plugins.phylotree.PhyloTreeArgProcessor.processOtu" message="ERR_BAD_SYNTAX [E. faecalis LMG 79377 (AJ843387)]" millis="11607"/>
 <error method="org.xmlcml.ami2.plugins.phylotree.PhyloTreeArgProcessor.processOtu" message="ERR_BAD_SYNTAX [E. saccharominimus LMG 217277 (AJ843425)]" millis="11607"/>
 <error method="org.xmlcml.ami2.plugins.phylotree.PhyloTreeArgProcessor.processOtu" message="ERR_BAD_SYNTAX [E. italicus LMG 220397 (AJ843426)]" millis="11607"/>
 <error method="org.xmlcml.ami2.plugins.phylotree.PhyloTreeArgProcessor.processOtu" message="ERR_BAD_SYNTAX [E. pseudoavium LMG 114267 (AJ843375)]" millis="11607"/>
 <error method="org.xmlcml.ami2.plugins.phylotree.PhyloTreeArgProcessor.processOtu" message="ERR_BAD_SYNTAX [E. faecium LMG 114237 (AJ843428)]" millis="11607"/>
 <error method="org.xmlcml.ami2.plugins.phylotree.PhyloTreeArgProcessor.processOtu" message="ERR_BAD_SYNTAX [E. cecorum LMG 129027 (AJ843416)]" millis="11607"/>
 <error method="org.xmlcml.ami2.plugins.phylotree.PhyloTreeArgProcessor.processOtu" message="ERR_BAD_SYNTAX [E. pallens LMG 218427 (AJ843397)]" millis="11607"/>
 <error method="org.xmlcml.ami2.plugins.phylotree.PhyloTreeArgProcessor.processOtu" message="ERR_BAD_SYNTAX [E. moraviensis LMG 194867 (AJ843422)]" millis="11607"/>
 <error method="org.xmlcml.ami2.plugins.phylotree.PhyloTreeArgProcessor.processOtu" message="ERR_BAD_SYNTAX [E. casseliflavus LMG 107457 (AJ843470)]" millis="11607"/>
 <error method="org.xmlcml.ami2.plugins.phylotree.PhyloTreeArgProcessor.processOtu" message="ERR_BAD_SYNTAX [E. f7avescens LMG 135187 (AJ843465)]" millis="11607"/>
 <error method="org.xmlcml.ami2.plugins.phylotree.PhyloTreeArgProcessor.processOtu" message="ERR_BAD_SYNTAX [E. raffinosus LMG 128887 (AJ843381)]" millis="11608"/>
 <error method="org.xmlcml.ami2.plugins.phylotree.PhyloTreeArgProcessor.processOtu" message="ERR_BAD_SYNTAX [E. phoeniculicola LMG 224717 (AJ843394)]" millis="11608"/>
 <error method="org.xmlcml.ami2.plugins.phylotree.PhyloTreeArgProcessor.processOtu" message="ERR_BAD_SYNTAX [E. hermanniensis LMG 123177 (AJ843380)]" millis="11608"/>
 <error method="org.xmlcml.ami2.plugins.phylotree.PhyloTreeArgProcessor.processOtu" message="ERR_BAD_SYNTAX [E. columbae LMG 117407 (AJ843417)]" millis="11608"/>
 <error method="org.xmlcml.ami2.plugins.phylotree.PhyloTreeArgProcessor.processOtu" message="ERR_BAD_SYNTAX [E. ratti LMG 218287 (AJ843386)]" millis="11608"/>
 <error method="org.xmlcml.ami2.plugins.phylotree.PhyloTreeArgProcessor.processOtu" message="ERR_BAD_SYNTAX [E. gilvus LMG 218417 (AJ843390)]" millis="11608"/>
 <error method="org.xmlcml.ami2.plugins.phylotree.PhyloTreeArgProcessor.processOtu" message="ERR_BAD_SYNTAX [E. gallinarum LMG 131297 (AJ843464)]" millis="11608"/>
 <error method="org.xmlcml.ami2.plugins.phylotree.PhyloTreeArgProcessor.processOtu" message="ERR_BAD_SYNTAX [E. haemoperoxidus LMG 194877 (AJ843415)]" millis="11608"/>
 <error method="org.xmlcml.ami2.plugins.phylotree.PhyloTreeArgProcessor.processOtu" message="ERR_BAD_SYNTAX [E. malodoratus LMG 107477 (AJ843429)]" millis="11608"/>
 <error method="org.xmlcml.ami2.plugins.phylotree.PhyloTreeArgProcessor.processOtu" message="ERR_BAD_SYNTAX [E. canis LMG 123167 (AJ843379)]" millis="11608"/>
 <error method="org.xmlcml.ami2.plugins.phylotree.PhyloTreeArgProcessor.processOtu" message="ERR_BAD_SYNTAX [E. avium LMG 107447 (AJ843457)]" millis="11608"/>
 <error method="org.xmlcml.ami2.plugins.phylotree.PhyloTreeArgProcessor.processOtu" message="ERR_BAD_SYNTAX [E. asini LMG 187277 (AJ843430)]" millis="11608"/>
 <error method="org.xmlcml.ami2.plugins.phylotree.PhyloTreeArgProcessor.pruneBadTips" message="cannot delete tip java.lang.RuntimeException: null parentEdge in elideIfHasSingletonChild" millis="11609"/>
 <info method="org.xmlcml.ami2.plugins.phylotree.PhyloTreeArgProcessor.pruneBadTips" message="deleted node NT1.30" millis="11609"/>
 <info method="org.xmlcml.ami2.plugins.phylotree.PhyloTreeArgProcessor.pruneBadTips" message="deleted node NT1.32" millis="11610"/>
 <info method="org.xmlcml.ami2.plugins.phylotree.PhyloTreeArgProcessor.pruneBadTips" message="deleted node NT1.33" millis="11610"/>
 <info method="org.xmlcml.ami2.plugins.phylotree.PhyloTreeArgProcessor.pruneBadTips" message="deleted node NT1.34" millis="11610"/>
 <info method="org.xmlcml.ami2.plugins.phylotree.PhyloTreeArgProcessor.pruneBadTips" message="deleted node NT1.35" millis="11611"/>
 <info method="org.xmlcml.ami2.plugins.phylotree.PhyloTreeArgProcessor.pruneBadTips" message="deleted node NT1.36" millis="11611"/>
 <info method="org.xmlcml.ami2.plugins.phylotree.PhyloTreeArgProcessor.pruneBadTips" message="deleted node NT1.37" millis="11611"/>
 <info method="org.xmlcml.ami2.plugins.phylotree.PhyloTreeArgProcessor.pruneBadTips" message="deleted node NT1.38" millis="11612"/>
 <info method="org.xmlcml.ami2.plugins.phylotree.PhyloTreeArgProcessor.pruneBadTips" message="deleted node NT1.39" millis="11612"/>
 <info method="org.xmlcml.ami2.plugins.phylotree.PhyloTreeArgProcessor.pruneBadTips" message="deleted node NT1.40" millis="11612"/>
 <info method="org.xmlcml.ami2.plugins.phylotree.PhyloTreeArgProcessor.pruneBadTips" message="deleted node NT1.41" millis="11612"/>
 <info method="org.xmlcml.ami2.plugins.phylotree.PhyloTreeArgProcessor.pruneBadTips" message="deleted node NT1.42" millis="11613"/>
 <info method="org.xmlcml.ami2.plugins.phylotree.PhyloTreeArgProcessor.pruneBadTips" message="deleted node NT1.43" millis="11613"/>
 <info method="org.xmlcml.ami2.plugins.phylotree.PhyloTreeArgProcessor.pruneBadTips" message="deleted node NT1.44" millis="11613"/>
 <info method="org.xmlcml.ami2.plugins.phylotree.PhyloTreeArgProcessor.pruneBadTips" message="deleted node NT1.45" millis="11614"/>
 <info method="org.xmlcml.ami2.plugins.phylotree.PhyloTreeArgProcessor.pruneBadTips" message="deleted node NT1.46" millis="11614"/>
 <info method="org.xmlcml.ami2.plugins.phylotree.PhyloTreeArgProcessor.pruneBadTips" message="deleted node NT1.48" millis="11614"/>
 <info method="org.xmlcml.ami2.plugins.phylotree.PhyloTreeArgProcessor.pruneBadTips" message="deleted node NT1.49" millis="11614"/>
 <info method="org.xmlcml.ami2.plugins.phylotree.PhyloTreeArgProcessor.pruneBadTips" message="deleted node NT1.50" millis="11615"/>
 <info method="org.xmlcml.ami2.plugins.phylotree.PhyloTreeArgProcessor.pruneBadTips" message="deleted node NT1.51" millis="11615"/>
 <info method="org.xmlcml.ami2.plugins.phylotree.PhyloTreeArgProcessor.pruneBadTips" message="deleted node NT1.52" millis="11615"/>
 <info method="org.xmlcml.ami2.plugins.phylotree.PhyloTreeArgProcessor.pruneBadTips" message="deleted node NT1.53" millis="11615"/>
 <info method="org.xmlcml.ami2.plugins.phylotree.PhyloTreeArgProcessor.pruneBadTips" message="deleted node NT1.54" millis="11615"/>
 <info method="org.xmlcml.ami2.plugins.phylotree.PhyloTreeArgProcessor.pruneBadTips" message="deleted node NT1.55" millis="11616"/>
 <info method="org.xmlcml.ami2.plugins.phylotree.PhyloTreeArgProcessor.pruneBadTips" message="deleted node NT1.56" millis="11616"/>
 <info method="org.xmlcml.ami2.plugins.phylotree.PhyloTreeArgProcessor.pruneBadTips" message="deleted node NT1.57" millis="11616"/>
 <info method="org.xmlcml.ami2.plugins.phylotree.PhyloTreeArgProcessor.pruneBadTips" message="deleted node NT1.58" millis="11616"/>
 <info method="org.xmlcml.ami2.plugins.phylotree.PhyloTreeArgProcessor.pruneBadTips" message="deleted node NT1.59" millis="11616"/>
 <info method="org.xmlcml.ami2.plugins.phylotree.PhyloTreeArgProcessor.pruneBadTips" message="deleted node NT1.60" millis="11617"/>
 <info method="org.xmlcml.ami2.plugins.phylotree.PhyloTreeArgProcessor.pruneBadTips" message="deleted node NT1.61" millis="11617"/>
 <info method="org.xmlcml.ami2.plugins.phylotree.PhyloTreeArgProcessor.pruneBadTips" message="deleted node NT1.62" millis="11617"/>
 <info method="org.xmlcml.ami2.plugins.phylotree.PhyloTreeArgProcessor.pruneBadTips" message="deleted node NT1.63" millis="11617"/>
 <info method="org.xmlcml.ami2.plugins.phylotree.PhyloTreeArgProcessor.pruneBadTips" message="deleted node NT1.64" millis="11617"/>
 <info method="org.xmlcml.ami2.plugins.phylotree.PhyloTreeArgProcessor.pruneBadTips" message="deleted node NT1.65" millis="11617"/>
 <info method="org.xmlcml.ami2.plugins.phylotree.PhyloTreeArgProcessor.pruneBadTips" message="deleted node NT1.66" millis="11618"/>
 <info method="org.xmlcml.ami2.plugins.phylotree.PhyloTreeArgProcessor.createTree" message="Analyzed pixels for tree successfully" millis="11619"/>
 <info method="org.xmlcml.ami2.plugins.phylotree.PhyloTreeArgProcessor.outputNexml" message="wrote NEXML: ../ijsem/500C/ijs.0.63752-0-001.pbm/results/phylotree/001.nexml.xml" millis="11620"/>
 <info method="org.xmlcml.ami2.plugins.phylotree.PhyloTreeArgProcessor.outputNewick" message="wrote Newick: ../ijsem/500C/ijs.0.63752-0-001.pbm/results/phylotree/001.nwk" millis="11621"/>
 <info method="org.xmlcml.ami2.plugins.phylotree.PhyloTreeArgProcessor.outputHocrSvg" message="wrote HOCSVG: ../ijsem/500C/ijs.0.63752-0-001.pbm/results/phylotree/001.hocr.svg" millis="11629"/>
 <info method="org.xmlcml.ami2.plugins.phylotree.PhyloTreeArgProcessor.outputSvg" message="wrote HOCSVG: ../ijsem/500C/ijs.0.63752-0-001.pbm/results/phylotree/001.svg" millis="11635"/>
</log>
