<?xml version="1.0" encoding="UTF-8"?>
<log date="2015-08-29T21:22:35.165+01:00">
 <info method="org.xmlcml.ami2.plugins.phylotree.PhyloTreeArgProcessor.ensureOutputDirectory" message="PhyloTree output to: target/junk/1440879755165; suggest you setOutputDir()" millis="0"/>
 <error method="org.xmlcml.ami2.plugins.phylotree.PhyloTreeArgProcessor.processOtu" message="ERR_BAD_SYNTAX []" millis="12113"/>
 <error method="org.xmlcml.ami2.plugins.phylotree.PhyloTreeArgProcessor.processOtu" message="ERR_BAD_SYNTAX [Methylobacterium radiotolerans JCM 2831 T (D32227)]" millis="12114"/>
 <error method="org.xmlcml.ami2.plugins.phylotree.PhyloTreeArgProcessor.processOtu" message="ERR_BAD_SYNTAX [Methylobacterium rhodesianum JCM 281 OT (D32228)]" millis="12114"/>
 <error method="org.xmlcml.ami2.plugins.phylotree.PhyloTreeArgProcessor.processOtu" message="ERR_BAD_SYNTAX [Methylobacterium Iusitanum RXMT (AY009403)]" millis="12117"/>
 <info method="org.xmlcml.ami2.plugins.phylotree.PhyloTreeArgProcessor.pruneBadTips" message="deleted node NT1.20" millis="12118"/>
 <info method="org.xmlcml.ami2.plugins.phylotree.PhyloTreeArgProcessor.pruneBadTips" message="deleted node NT1.22" millis="12119"/>
 <info method="org.xmlcml.ami2.plugins.phylotree.PhyloTreeArgProcessor.pruneBadTips" message="deleted node NT1.26" millis="12119"/>
 <info method="org.xmlcml.ami2.plugins.phylotree.PhyloTreeArgProcessor.pruneBadTips" message="deleted node NT1.43" millis="12119"/>
 <info method="org.xmlcml.ami2.plugins.phylotree.PhyloTreeArgProcessor.createTree" message="Analyzed pixels for tree successfully" millis="12125"/>
 <info method="org.xmlcml.ami2.plugins.phylotree.PhyloTreeArgProcessor.outputNexml" message="wrote NEXML: ../ijsem/500F/ijs.0.63966-0-000.pbm/results/phylotree/001.nexml.xml" millis="12125"/>
 <info method="org.xmlcml.ami2.plugins.phylotree.PhyloTreeArgProcessor.outputNewick" message="wrote Newick: ../ijsem/500F/ijs.0.63966-0-000.pbm/results/phylotree/001.nwk" millis="12128"/>
 <info method="org.xmlcml.ami2.plugins.phylotree.PhyloTreeArgProcessor.outputHocrSvg" message="wrote HOCSVG: ../ijsem/500F/ijs.0.63966-0-000.pbm/results/phylotree/001.hocr.svg" millis="12133"/>
 <info method="org.xmlcml.ami2.plugins.phylotree.PhyloTreeArgProcessor.outputSvg" message="wrote HOCSVG: ../ijsem/500F/ijs.0.63966-0-000.pbm/results/phylotree/001.svg" millis="12138"/>
</log>
